{
  "@context": {
    "@import": "https://schema.org/",
    "schema": "https://schema.org/"
  },
  "@id": "https://w3id.org/marco-bolo/mbo_contact_nick-input-metadata",
  "@reverse": {
    "result": {
      "@id": "https://w3id.org/marco-bolo/mbo_wp1_t1_1"
    }
  },
  "@type": "Dataset",
  "about": {
    "@id": "https://w3id.org/marco-bolo/mbo_contact_nick"
  },
  "archivedAt": "https://github.com/marco-bolo/csv-to-json-ld/tree/8a150518435403fa2d0cf0f1d106bcaf6e552e46",
  "creator": {
    "@id": "https://w3id.org/marco-bolo/mbo_roblinksdata"
  },
  "distribution": [
    {
      "@id": "https://w3id.org/marco-bolo/mbo_contact_nick-input-metadata#csv",
      "@reverse": {
        "result": {
          "@id": "https://w3id.org/marco-bolo/mbo_wp1_t1_1"
        }
      },
      "@type": "DataDownload",
      "about": {
        "@id": "https://w3id.org/marco-bolo/mbo_contact_nick"
      },
      "schema:contentUrl": {
        "@type": "URL",
        "@value": "https://w3id.org/marco-bolo/mbo_0000006#row=2"
      },
      "creator": {
        "@id": "https://w3id.org/marco-bolo/mbo_roblinksdata"
      },
      "encodesCreativeWork": {
        "@id": "https://w3id.org/marco-bolo/mbo_contact_nick-input-metadata"
      },
      "encodingFormat": "text/csv"
    },
    {
      "@id": "https://w3id.org/marco-bolo/mbo_contact_nick-input-metadata#jsonld",
      "@reverse": {
        "result": {
          "@id": "https://w3id.org/marco-bolo/mbo_wp1_t1_1"
        }
      },
      "@type": "DataDownload",
      "about": {
        "@id": "https://w3id.org/marco-bolo/mbo_contact_nick"
      },
      "schema:contentUrl": {
        "@type": "URL",
        "@value": "https://w3id.org/marco-bolo/mbo_contact_nick"
      },
      "creator": {
        "@id": "https://w3id.org/marco-bolo/mbo_todo_organization_mbo"
      },
      "dateModified": "2026-01-11",
      "encodesCreativeWork": {
        "@id": "https://w3id.org/marco-bolo/mbo_contact_nick-input-metadata"
      },
      "encodingFormat": "application/ld+json"
    }
  ]
}
