{
  "@context": {
    "@import": "https://schema.org/",
    "schema": "https://schema.org/"
  },
  "@id": "https://w3id.org/marco-bolo/mbo_9c13b8c0-5143-4b51-9de7-1c848f7a8d23",
  "@type": "DigitalDocument",
  "abstract": "Sustainable monitoring of organisms and their habitats is imperative during the biodiversity crisis, and is especially important in marine waters where fisheries alone feed approximately 3 billion people globally while multiple threats change ecosystem dynamics. MARCO BOLO's WP4 aims to create a direct pipeline from non-invasive, in situ monitoring of marine life, to ocean users and managers. WP4 aims to achieve this through adoption of workflows developed in WP1, FAIR data reporting, automated classification of high-volume datasets, and geolocation of sensed data in near-real-time. The first 18 months of MARCO BOLO resulted in the development of several new deployable technologies to measure biodiversity, enabling geolocation in the field, simplicity in interacting with the software and datasets, automated classification and data processing, and enabling data flows from high-volume datasets to public repositories. While not yet field-tested, the developments described here already enable the reporting of biodiversity datasets for mapping and response, detecting ecosystems and their prey, and counting and communicating species data from the field. One publication describing these new biodiversity systems is open-access and another has been submitted. The WP4 team aims to demonstrate these developments in June 2025 in the Belgian North Sea. This report describes the progress made in the first 18 months of MARCO BOLO WP4, Task 4.1, to 'develop autonomous systems to deliver georeferenced maps of biodiversity attributes including genomic, taxonomic and habitat characteristics.' Deliverable 4.1 is achieved through seven complementary technologies targeting diverse biodiversity variables, organized across four sub-objectives: Genomics (upgrading the Robotic Cartridge Sampling Instrument (RoCSI) sampler and the LAMPTRON eDNA sensor to facilitate geolocation, data delivery, and usability); Particulate and plankton imaging (integrating the UVP6 into autonomous vehicles with on-board image processing using a miniaturized AI system for real-time image classification); Fish and benthos (integrating Ultra Short Base Line (USBL) acoustics for positioning of an open-source BlueROV2 ROV with a new high-definition multi-camera system; outputs include processed large-scale seafloor images and annotations of identified animals); and Bioacoustics (developing a stand-alone mooring accommodating an acoustic fish receiver, a broadband hydrophone, and a C-POD/F-POD device for long-term recording at sea, with a data pipeline for detection and classification of harbour porpoise (Phocoena phocoena) echolocation click trains and export to EMODnet Biology and EurOBIS following FAIR principles).",
  "alternateName": "D4.1",
  "author": [
    {
      "@id": "https://w3id.org/marco-bolo/mbo_9145a8c8-d293-4b86-9344-368d94d43599"
    },
    {
      "@id": "https://w3id.org/marco-bolo/mbo_1563b216-98e8-47ed-a413-19b56c373d1c"
    },
    {
      "@id": "https://w3id.org/marco-bolo/mbo_74d8ae60-3d99-4c28-8f62-192e484fa5d9"
    },
    {
      "@id": "https://w3id.org/marco-bolo/mbo_6c6a182c-469a-4828-a335-39359af3eb61"
    },
    {
      "@id": "https://w3id.org/marco-bolo/mbo_fb5f8c5d-c22b-429f-a0bc-700ae161033c"
    },
    {
      "@id": "https://w3id.org/marco-bolo/mbo_d6e4f709-3431-4ccb-9968-1d8bbb404941"
    },
    {
      "@id": "https://w3id.org/marco-bolo/mbo_9c62c2f4-582f-4435-b576-951b0e53c8a5"
    }
  ],
  "availableLanguage": "en",
  "contributor": {
    "@id": "https://w3id.org/marco-bolo/mbo_15f6ae40-8607-4c27-b7d4-d46b57e2ecb7"
  },
  "creativeWorkStatus": {
    "@id": "https://w3id.org/marco-bolo/mbo_c2fb3abb-2a8e-420b-8059-271b57a95840"
  },
  "schema:dateCreated": "2024-03-31",
  "schema:datePublished": "2024-06-25",
  "description": "Preliminary report on progress for advanced data processing, geolocation and export format",
  "identifier": [
    "Deliverable D4.1",
    "doi:10.5281/zenodo.20779638"
  ],
  "keywords": [
    "geolocation",
    "autonomous sensors",
    "marine instrumentation",
    "MBO WP4",
    "biodiversity monitoring"
  ],
  "license": "https://w3id.org/marco-bolo/mbo_500ee36e-324d-4f2f-9b0b-a4408f638201",
  "name": "MARCO-BOLO Deliverable D4.1 - Preliminary report on progress for advanced data processing, geolocation and export format",
  "schema:url": [
    {
      "@type": "URL",
      "@value": "https://doi.org/10.5281/zenodo.20779638"
    },
    {
      "@type": "URL",
      "@value": "https://marcobolo-project.eu/wp-content/uploads/2024/08/MBO_D4.1_Jun-2024.pdf"
    },
    {
      "@type": "URL",
      "@value": "https://zenodo.org/records/20779638"
    }
  ],
  "version": "1"
}
