{
    "@context": "http://www.w3.org/ns/csvw",
    "tables": [
        {
            "url": "../contact-point.csv",
            "tableSchema": "contact-point.schema.json",
            "suppressOutput": true
        },
        {
            "url": "../create-action.csv",
            "tableSchema": "create-action.schema.json",
            "suppressOutput": true
        },
        {
            "url": "../data-download.csv",
            "tableSchema": "data-download.schema.json",
            "suppressOutput": true
        },
        {
            "url": "../dataset.csv",
            "tableSchema": "dataset.schema.json",
            "suppressOutput": true
        },
        {
            "url": "../dataset-comment.csv",
            "tableSchema": "dataset-comment.schema.json"
        },
        {
            "url": "../license.csv",
            "tableSchema": "license.schema.json",
            "suppressOutput": true
        },
        {
            "url": "../monetary-grant.csv",
            "tableSchema": "monetary-grant.schema.json",
            "suppressOutput": true
        },
        {
            "url": "../organization.csv",
            "tableSchema": "organization.schema.json",
            "suppressOutput": true
        },
        {
            "url": "../person.csv",
            "tableSchema": "person.schema.json",
            "suppressOutput": true
        },
        {
            "url": "../out/validation/person-or-organization.csv",
            "tableSchema": "unioned-identifiers.schema.json",
            "suppressOutput": true
        },
        {
            "url": "../variable-measured.csv",
            "tableSchema": "variable-measured.schema.json",
            "suppressOutput": true
        }
    ]
}